{
    "points": [
        {
            "coordinate": [
                472.5,
                119.5
            ],
            "type": "invisible",
            "id": "1-1",
            "label": "Head tip"
        },
        {
            "coordinate": [
                508.5,
                285.5
            ],
            "type": "visible",
            "id": "2-2",
            "label": "Neck"
        },
        {
            "coordinate": [
                641.5000247871094,
                299.44886206738283
            ],
            "type": "visible",
            "id": "3-3",
            "label": "Left shoulder"
        },
        {
            "coordinate": [
                405.5,
                342.5
            ],
            "type": "visible",
            "id": "4-4",
            "label": "Right shoulder"
        },
        {
            "coordinate": [
                670.5,
                534.5
            ],
            "type": "invisible",
            "id": "5-5",
            "label": "Left elbow"
        },
        {
            "coordinate": [
                396.5,
                532.5
            ],
            "type": "invisible",
            "id": "6-6",
            "label": "Right elbow"
        },
        {
            "coordinate": [
                681.5,
                677.5
            ],
            "type": "invisible",
            "id": "7-7",
            "label": "Left wrist"
        },
        {
            "coordinate": [
                382.5,
                686.5
            ],
            "type": "invisible",
            "id": "8-8",
            "label": "Right wrist"
        },
        {
            "coordinate": [
                684.5,
                744.5
            ],
            "type": "invisible",
            "id": "9-9",
            "label": "Left palm center"
        },
        {
            "coordinate": [
                373.5,
                717.5
            ],
            "type": "invisible",
            "id": "10-10",
            "label": "Right palm center"
        },
        {
            "coordinate": [
                594.5,
                569.5
            ],
            "type": "invisible",
            "id": "11-11",
            "label": "Left hip"
        },
        {
            "coordinate": [
                427.5,
                559.5
            ],
            "type": "invisible",
            "id": "12-12",
            "label": "Right hip"
        },
        {
            "coordinate": [
                690.5,
                968.5
            ],
            "type": "invisible",
            "id": "13-13",
            "label": "Left knee"
        },
        {
            "coordinate": [
                461.75,
                956
            ],
            "type": "visible",
            "id": "14-14",
            "label": "Right knee"
        },
        {
            "coordinate": [
                743.7500247871094,
                1248.4488620673828
            ],
            "type": "invisible",
            "id": "15-15",
            "label": "Left ankle"
        },
        {
            "coordinate": [
                536.75,
                1252
            ],
            "type": "invisible",
            "id": "16-16",
            "label": "Right ankle"
        },
        {
            "coordinate": [
                826.75,
                1331
            ],
            "type": "invisible",
            "id": "17-17",
            "label": "Left tiptoe"
        },
        {
            "coordinate": [
                550.75,
                1344
            ],
            "type": "invisible",
            "id": "18-18",
            "label": "Right tiptoe"
        }
    ],
    "title": "session_04/01457-female-adult-yellow-outdoor.jpg"
}