{
    "points": [
        {
            "coordinate": [
                136.7777604902344,
                365.54512499218754
            ],
            "type": "invisible",
            "id": "1-1",
            "label": "Head tip"
        },
        {
            "coordinate": [
                197.7777604902344,
                420.54512499218754
            ],
            "type": "invisible",
            "id": "2-2",
            "label": "Neck"
        },
        {
            "coordinate": [
                155.7777604902344,
                384.54512499218754
            ],
            "type": "visible",
            "id": "3-3",
            "label": "Left shoulder"
        },
        {
            "coordinate": [
                302.7777604902344,
                401.54512499218754
            ],
            "type": "invisible",
            "id": "4-4",
            "label": "Right shoulder"
        },
        {
            "coordinate": [
                158.7777604902344,
                579.5451249921875
            ],
            "type": "visible",
            "id": "5-5",
            "label": "Left elbow"
        },
        {
            "coordinate": [
                324.2777604902344,
                598.0451249921875
            ],
            "type": "visible",
            "id": "6-6",
            "label": "Right elbow"
        },
        {
            "coordinate": [
                179.7777604902344,
                741.0451249921875
            ],
            "type": "invisible",
            "id": "7-7",
            "label": "Left wrist"
        },
        {
            "coordinate": [
                321.7777604902344,
                729.0451249921875
            ],
            "type": "invisible",
            "id": "8-8",
            "label": "Right wrist"
        },
        {
            "coordinate": [
                147.7777604902344,
                740.0451249921875
            ],
            "type": "invisible",
            "id": "9-9",
            "label": "Left palm center"
        },
        {
            "coordinate": [
                297.7777604902344,
                731.0451249921875
            ],
            "type": "invisible",
            "id": "10-10",
            "label": "Right palm center"
        },
        {
            "coordinate": [
                343.7777604902344,
                496.04512499218754
            ],
            "type": "invisible",
            "id": "11-11",
            "label": "Left hip"
        },
        {
            "coordinate": [
                429.7777604902344,
                483.04512499218754
            ],
            "type": "invisible",
            "id": "12-12",
            "label": "Right hip"
        },
        {
            "coordinate": [
                610.7777604902344,
                579.0451249921875
            ],
            "type": "visible",
            "id": "13-13",
            "label": "Left knee"
        },
        {
            "coordinate": [
                661.7777604902344,
                573.0451249921875
            ],
            "type": "invisible",
            "id": "14-14",
            "label": "Right knee"
        },
        {
            "coordinate": [
                884.7777604902344,
                681.0451249921875
            ],
            "type": "visible",
            "id": "15-15",
            "label": "Left ankle"
        },
        {
            "coordinate": [
                924.7777604902344,
                675.0451249921875
            ],
            "type": "invisible",
            "id": "16-16",
            "label": "Right ankle"
        },
        {
            "coordinate": [
                833.2777604902344,
                768.5451249921875
            ],
            "type": "visible",
            "id": "17-17",
            "label": "Left tiptoe"
        },
        {
            "coordinate": [
                893.7777604902344,
                760.0451249921875
            ],
            "type": "invisible",
            "id": "18-18",
            "label": "Right tiptoe"
        }
    ],
    "title": "session_04/01837-female-adult-yellow-indoor.jpg"
}