{
    "points": [
        {
            "coordinate": [
                391.5,
                84.5
            ],
            "type": "invisible",
            "id": "1-1",
            "label": "Head tip"
        },
        {
            "coordinate": [
                357.5,
                165.5
            ],
            "type": "visible",
            "id": "2-2",
            "label": "Neck"
        },
        {
            "coordinate": [
                396.25,
                175
            ],
            "type": "invisible",
            "id": "3-3",
            "label": "Left shoulder"
        },
        {
            "coordinate": [
                287.75,
                179
            ],
            "type": "invisible",
            "id": "4-4",
            "label": "Right shoulder"
        },
        {
            "coordinate": [
                411,
                251
            ],
            "type": "invisible",
            "id": "5-5",
            "label": "Left elbow"
        },
        {
            "coordinate": [
                256.25,
                261
            ],
            "type": "invisible",
            "id": "6-6",
            "label": "Right elbow"
        },
        {
            "coordinate": [
                425,
                294
            ],
            "type": "visible",
            "id": "7-7",
            "label": "Left wrist"
        },
        {
            "coordinate": [
                323,
                293.5
            ],
            "type": "visible",
            "id": "8-8",
            "label": "Right wrist"
        },
        {
            "coordinate": [
                410.5,
                314.5
            ],
            "type": "visible",
            "id": "9-9",
            "label": "Left palm center"
        },
        {
            "coordinate": [
                339.75,
                313.5
            ],
            "type": "visible",
            "id": "10-10",
            "label": "Right palm center"
        },
        {
            "coordinate": [
                396.25,
                313.5
            ],
            "type": "invisible",
            "id": "11-11",
            "label": "Left hip"
        },
        {
            "coordinate": [
                342.25,
                317.5
            ],
            "type": "invisible",
            "id": "12-12",
            "label": "Right hip"
        },
        {
            "coordinate": [
                376.75,
                469
            ],
            "type": "invisible",
            "id": "13-13",
            "label": "Left knee"
        },
        {
            "coordinate": [
                396.25,
                459.5
            ],
            "type": "visible",
            "id": "14-14",
            "label": "Right knee"
        },
        {
            "coordinate": [
                369,
                566.5
            ],
            "type": "visible",
            "id": "15-15",
            "label": "Left ankle"
        },
        {
            "coordinate": [
                337,
                563
            ],
            "type": "visible",
            "id": "16-16",
            "label": "Right ankle"
        },
        {
            "coordinate": [
                378.75,
                614.5
            ],
            "type": "visible",
            "id": "17-17",
            "label": "Left tiptoe"
        },
        {
            "coordinate": [
                338,
                610.5
            ],
            "type": "visible",
            "id": "18-18",
            "label": "Right tiptoe"
        }
    ],
    "title": "session_04/02587-female-adult-yellow-indoor.jpg"
}