{
    "points": [
        {
            "coordinate": [
                793.5,
                123.5
            ],
            "type": "invisible",
            "id": "1-1",
            "label": "Head tip"
        },
        {
            "coordinate": [
                645.5,
                321.5
            ],
            "type": "visible",
            "id": "2-2",
            "label": "Neck"
        },
        {
            "coordinate": [
                765.5,
                409.5
            ],
            "type": "invisible",
            "id": "3-3",
            "label": "Left shoulder"
        },
        {
            "coordinate": [
                534.5,
                285.5
            ],
            "type": "invisible",
            "id": "4-4",
            "label": "Right shoulder"
        },
        {
            "coordinate": [
                715.5,
                664.5
            ],
            "type": "visible",
            "id": "5-5",
            "label": "Left elbow"
        },
        {
            "coordinate": [
                396.5,
                462.5
            ],
            "type": "visible",
            "id": "6-6",
            "label": "Right elbow"
        },
        {
            "coordinate": [
                817.5,
                449.5
            ],
            "type": "visible",
            "id": "7-7",
            "label": "Left wrist"
        },
        {
            "coordinate": [
                251.5,
                450.5
            ],
            "type": "invisible",
            "id": "8-8",
            "label": "Right wrist"
        },
        {
            "coordinate": [
                800.5,
                387.5
            ],
            "type": "visible",
            "id": "9-9",
            "label": "Left palm center"
        },
        {
            "coordinate": [
                621.5,
                702.5
            ],
            "type": "invisible",
            "id": "11-11",
            "label": "Left hip"
        },
        {
            "coordinate": [
                423.5,
                624.5
            ],
            "type": "invisible",
            "id": "12-12",
            "label": "Right hip"
        },
        {
            "coordinate": [
                437.5,
                923.5
            ],
            "type": "visible",
            "id": "13-13",
            "label": "Left knee"
        },
        {
            "coordinate": [
                372.5,
                935.5
            ],
            "type": "visible",
            "id": "14-14",
            "label": "Right knee"
        },
        {
            "coordinate": [
                308.5,
                1067.5
            ],
            "type": "visible",
            "id": "15-15",
            "label": "Left ankle"
        },
        {
            "coordinate": [
                270.5,
                1049.5
            ],
            "type": "visible",
            "id": "16-16",
            "label": "Right ankle"
        }
    ],
    "title": "session_04/02720-female-adult-yellow-indoor.jpg"
}