{
    "points": [
        {
            "coordinate": [
                313.09999084472656,
                26.800003051757812
            ],
            "type": "invisible",
            "id": "1-1",
            "label": "Head tip"
        },
        {
            "coordinate": [
                314.59999084472656,
                115.80000305175781
            ],
            "type": "visible",
            "id": "2-2",
            "label": "Neck"
        },
        {
            "coordinate": [
                369.09999084472656,
                128.3000030517578
            ],
            "type": "invisible",
            "id": "3-3",
            "label": "Left shoulder"
        },
        {
            "coordinate": [
                261.59999084472656,
                140.3000030517578
            ],
            "type": "invisible",
            "id": "4-4",
            "label": "Right shoulder"
        },
        {
            "coordinate": [
                383.59999084472656,
                206.8000030517578
            ],
            "type": "visible",
            "id": "5-5",
            "label": "Left elbow"
        },
        {
            "coordinate": [
                259.34999084472656,
                222.5500030517578
            ],
            "type": "invisible",
            "id": "6-6",
            "label": "Right elbow"
        },
        {
            "coordinate": [
                360.84999084472656,
                238.8000030517578
            ],
            "type": "visible",
            "id": "7-7",
            "label": "Left wrist"
        },
        {
            "coordinate": [
                273.34999084472656,
                239.0500030517578
            ],
            "type": "invisible",
            "id": "8-8",
            "label": "Right wrist"
        },
        {
            "coordinate": [
                344.84999084472656,
                232.0500030517578
            ],
            "type": "visible",
            "id": "9-9",
            "label": "Left palm center"
        },
        {
            "coordinate": [
                293.34999084472656,
                243.0500030517578
            ],
            "type": "visible",
            "id": "10-10",
            "label": "Right palm center"
        },
        {
            "coordinate": [
                360.09999084472656,
                246.5500030517578
            ],
            "type": "invisible",
            "id": "11-11",
            "label": "Left hip"
        },
        {
            "coordinate": [
                281.34999084472656,
                247.3000030517578
            ],
            "type": "invisible",
            "id": "12-12",
            "label": "Right hip"
        },
        {
            "coordinate": [
                318.34999084472656,
                426.3000030517578
            ],
            "type": "visible",
            "id": "13-13",
            "label": "Left knee"
        },
        {
            "coordinate": [
                296.09999084472656,
                424.8000030517578
            ],
            "type": "visible",
            "id": "14-14",
            "label": "Right knee"
        },
        {
            "coordinate": [
                293.34999084472656,
                545.8000030517578
            ],
            "type": "visible",
            "id": "15-15",
            "label": "Left ankle"
        },
        {
            "coordinate": [
                320.84999084472656,
                514.0500030517578
            ],
            "type": "visible",
            "id": "16-16",
            "label": "Right ankle"
        },
        {
            "coordinate": [
                334.59999084472656,
                570.8000030517578
            ],
            "type": "invisible",
            "id": "17-17",
            "label": "Left tiptoe"
        },
        {
            "coordinate": [
                293.59999084472656,
                604.0500030517578
            ],
            "type": "invisible",
            "id": "18-18",
            "label": "Right tiptoe"
        }
    ],
    "title": "session_04/02843-female-adult-yellow-indoor.jpg"
}