{
    "points": [
        {
            "coordinate": [
                716,
                61.5
            ],
            "type": "invisible",
            "id": "1-1",
            "label": "Head tip"
        },
        {
            "coordinate": [
                626,
                191.5
            ],
            "type": "invisible",
            "id": "2-2",
            "label": "Neck"
        },
        {
            "coordinate": [
                717.5,
                262
            ],
            "type": "invisible",
            "id": "3-3",
            "label": "Left shoulder"
        },
        {
            "coordinate": [
                532,
                165.5
            ],
            "type": "invisible",
            "id": "4-4",
            "label": "Right shoulder"
        },
        {
            "coordinate": [
                672,
                435.5
            ],
            "type": "invisible",
            "id": "5-5",
            "label": "Left elbow"
        },
        {
            "coordinate": [
                503,
                328.75
            ],
            "type": "invisible",
            "id": "6-6",
            "label": "Right elbow"
        },
        {
            "coordinate": [
                693,
                306.5
            ],
            "type": "visible",
            "id": "7-7",
            "label": "Left wrist"
        },
        {
            "coordinate": [
                639,
                359.5
            ],
            "type": "invisible",
            "id": "8-8",
            "label": "Right wrist"
        },
        {
            "coordinate": [
                682,
                264.5
            ],
            "type": "visible",
            "id": "9-9",
            "label": "Left palm center"
        },
        {
            "coordinate": [
                676.5,
                369.5
            ],
            "type": "invisible",
            "id": "10-10",
            "label": "Right palm center"
        },
        {
            "coordinate": [
                651,
                467.75
            ],
            "type": "invisible",
            "id": "11-11",
            "label": "Left hip"
        },
        {
            "coordinate": [
                516,
                486.75
            ],
            "type": "invisible",
            "id": "12-12",
            "label": "Right hip"
        },
        {
            "coordinate": [
                580.5,
                733.5
            ],
            "type": "invisible",
            "id": "13-13",
            "label": "Left knee"
        },
        {
            "coordinate": [
                480.5,
                731.5
            ],
            "type": "invisible",
            "id": "14-14",
            "label": "Right knee"
        },
        {
            "coordinate": [
                523.5,
                898.5
            ],
            "type": "invisible",
            "id": "15-15",
            "label": "Left ankle"
        },
        {
            "coordinate": [
                459.5,
                885.5
            ],
            "type": "invisible",
            "id": "16-16",
            "label": "Right ankle"
        },
        {
            "coordinate": [
                489,
                959.25
            ],
            "type": "invisible",
            "id": "17-17",
            "label": "Left tiptoe"
        },
        {
            "coordinate": [
                446,
                956.25
            ],
            "type": "invisible",
            "id": "18-18",
            "label": "Right tiptoe"
        }
    ],
    "title": "session_04/09412-female-adult-yellow-indoor.jpg"
}